{
  "name": "Ollie Taylor",
  "age": 43,
  "address": {
    "street": "Lieh Street",
    "city": "Ommonced",
    "state": "KS",
    "zip": "90448"
  },
  "contact": {
    "phone": "(373) 709-3718",
    "servicePhone": "800587171"
  },
  "birthday": "1970-01-31T04:49:20.009Z",
  "ip": "215.145.137.162",
  "foo": "bar",
  "profile": {
    "about": "Difu hazregu mutlun mewuobe es gi la ki veihnuk zase vib malfupe turfep loipiti wadcujo avip uvu. Gatdum nogmug vojwa igibodic duzo sata ducatke zanof zujkadeli ep horar ju doug gumoizo. Lu ofa ca hi pefub medjomma kananofe iraje cu pes seraw faehuk jolnik lud nugful. Bi mor bog ufrugnob fugilca va fa ogoogu arin vitjow tumuve hirsa dur gobijoso najelejo. Riftabma iw waesegu fe hoharu bu neelimu dave zu tigioju konehi kulnefbis wotit itije. Cen rurrado maznogo zato lartalto hu atfagir tutne nuw jemves iz abairzar tu hive laf.",
    "bio": "Obe zomamef padmobju logpawube licsa hovetow etenaset oviazovur ibropzez govca tofage kizvava kolani. Lulbuhu lobufe jahen anu gegkuzin vegica najzi muv gohecab caan awuvipte ecnerca asape pi. Opuzote canziiz gusec hitviki daogo sak huim dej kuk osanucud owhaf noga tohnezu bimutcaf tog."
  },
  "apiKey": "60300caaa9e4e865c15477223d7713318c78ecd910e7adb1d45f3ddf6335af6e",
  "currency": {
    "code": "BBD",
    "name": "Barbados Dollar"
  }
}