{
  "name": "Russell Hopkins",
  "age": 37,
  "address": {
    "street": "Okeuh Ridge",
    "city": "Doazenuk",
    "state": "TN",
    "zip": "85893"
  },
  "contact": {
    "phone": "(809) 330-4122",
    "servicePhone": "800176443"
  },
  "birthday": "2006-06-21T01:28:41.604Z",
  "ip": "48.23.137.106",
  "foo": "bar",
  "profile": {
    "about": "Riwzof hag zegujif nujkajcec vif gat sihut ec cunsiku kuj jug oppeuh miw dien maice ezo. Daduhow visejfa jecji ulfaf civcejpah goos onju se uswori fo gedoh fivu jozesu izipa. Hoho nawde umawub niffal leg bat veboufa taw ice po peolijaj ujco filmuori la ude hadav woj. Ifuucisa sufom revid acoke vovawdup loh in jucois siki ageketo saakmil patvudep rozno guliwew bal alivego ithehuj.",
    "bio": "Rospow rehirbi vaskicti ke cireho leh kez puzmod evocivego umifu otbi wep tegzivmu izivac nomjod biha he. Bad wib sucaek pofnegu za dali veclotus gad aswammoz koso murezned ubuposup. Jod dew gin gasacwe cib revhizkaz naruto uzamu wirratwed nica zi vazpo hefozcaz mu dounuku kobnobeki. Sel pagukoki sedom un uctenar caj capvil meh babirwoj sujsac agwi olo vafon kuwiguatu taav vospugo netu vut. Zejutci pis gegov uvuzewu onmaga ha rapuvjun amzizub zusi akaloehu ag obejigbe biwtobbe souco cet doumunos."
  },
  "apiKey": "1f7348c833bc74fa7839239732e9ea9a6a8bc821782327583c09290bd2b842ff",
  "currency": {
    "code": "GBP",
    "name": "United Kingdom Pound"
  }
}