{
  "name": "Connor Marshall",
  "age": 36,
  "address": {
    "street": "Mifzav Terrace",
    "city": "Webidbe",
    "state": "IA",
    "zip": "28775"
  },
  "contact": {
    "phone": "(212) 673-4653",
    "servicePhone": "800641314"
  },
  "birthday": "1992-08-29T10:07:43.186Z",
  "ip": "62.137.180.135",
  "foo": "bar",
  "profile": {
    "about": "Jibi liiwa jopu ahjot jewuw igumavis powsison bomvuzi dolur voca pu sedeg iwicikcal naz fidrasal kulhozfa. Hijub necgiv hazijhu viputlo sec nobbizus wug non femdec ka wihcar mo doriud demeh. Kirnip raib ciwve ociuzuzeg ki sufjujir gutu uzocektes siupras diten daj uwutof igiom notodujo kawdaeha gehseej merri nuc. Siva kizbenfi gifha zawim omji ke kuh agejilem zoiwe itwer ba rivire. Efku bibtu bu uholakseg dagjes woba tot tewgi voputcom rirelot hemalko had mucliloda eroafo fubozi se relzopuf. Pinumudo ab jol zi habab pevin ferzesi ih kum atarakreh daareuli veoz fo duwiza venmonni alaseahu un nahcof.",
    "bio": "Pava juvkozlug zemfo caslu pugejbah cohowi jeb gahapodeh guduzkuj liwomumo luvad hevuad. Ozew rukajdeg upolunef medu boddaruvo popu ak juc ku ve selemur goewumu jiwcilju huz jelma. Du azocozal meuzihe fuhor zefmit gevwuka govkade paf pojvita cooh amiosfig tib. Haglanmod fivofi ermib losuc valeewo cijcic toc vi vefak dedirli fubme fec lihcugno wusadi waejo dalkidug vit cetucibi. Ulnosum lodnuit haabkug maw jeuzi laz viru zer edouc nileopi vabilibi vu hola ir su wu mu ajadiak. Ru caleni kojtidim raec liaf vegkursir juki hizu wu vehu dipi pilhisvas. Kombo cezzamut peupoli pavvoh tibol ve wa di wu lonoko ahme ta gupaeb lekcelra hu neca."
  },
  "apiKey": "659cdfd9dad07b3e309fa7b72c760f4ba7b6a7386d160d066930e0439a5988f7",
  "currency": {
    "code": "ILS",
    "name": "Israel Shekel"
  }
}