{
  "name": "Ian Burke",
  "age": 51,
  "address": {
    "street": "Mofhuh Road",
    "city": "Kuzfockac",
    "state": "AZ",
    "zip": "49097"
  },
  "contact": {
    "phone": "(322) 988-3960",
    "servicePhone": "800234165"
  },
  "birthday": "1967-02-03T12:37:18.576Z",
  "ip": "39.129.92.72",
  "foo": "bar",
  "profile": {
    "about": "Lamme nefuigi dem gedfos adi ikasi madeglij otufaw wew cecepa zugeza wihafke decergum ilnow. Vin cejmafhuk zekuuda demibbe wukaktur cavijkah lacapzi mali zaf cizror uwdokha fudkigcot bo. Coum izion tar ewe cupmu woehva dohefup buc cidfuzti mimsapkas oca uco turemzo igpis. Fusubna fan wesjuw kaiz evwodom viroce eleza zudnomce fuc aj zo jeno. Nunuhlof hewius hufur tetar ago owulohlec uchivupi jesru me sidotarin vep wi hu ofu unizioj zuj ot ko. Tafnarhud bikeso ja zidpaven ejzepum vilik ufele hu hefuru tajuskaf geb ikori bitah eswuweza eli ruom di. Fajes okuiku ite kapbib izhueno ilatup te hefiko larij poubho hu rete nun ud.",
    "bio": "Fintunvi afeiwa wadugcot nete rideci nab weuku wahhir ut rom vanu od hohni nughuv ire magjaz. Ruzmub widefjah nelliz gi arunu upauzev ig vo za diowmel on ipizeid sihgewe hefwuz sa jog. Awga holsez neniri usimomtuz ohekud ubukwib fauwicab osafahev ohwigo isusaevi hohaiz huopimem. Kewupa tahlup ruwbucuk dinitim goh zogmowum ucu ril nepesosi huwhu dop caf buloc wumagzo guhojiz. Oh zecusson vihe ja jot wonkufu ruev pipkicok temimice hoob feazso nur mitcuv no ewkeb. Lerju ju gipzinli one pubadomis nelrosa jab ag ihida giro tudnuwce julhajna."
  },
  "apiKey": "69fe260b1ad8b4c77b140fc1340819ce7322a7e33854250b58a269229dee7bcf",
  "currency": {
    "code": "KGS",
    "name": "Kyrgyzstan Som"
  }
}